grept/__init__.py
grept/__main__.py
grept/completions.py
grept/config.py
grept/embed.py
grept/interactive.py
grept/util.py
GrePT-1.3.0.dist-info/LICENSE.md
GrePT-1.3.0.dist-info/METADATA
GrePT-1.3.0.dist-info/WHEEL
GrePT-1.3.0.dist-info/entry_points.txt
GrePT-1.3.0.dist-info/top_level.txt
GrePT-1.3.0.dist-info/RECORD
