Metadata-Version: 2.1
Name: GrePT
Version: 1.3.0
Summary: Talk to your code
Author-email: Jack Barry <jack.barry@live.com>
Project-URL: Homepage, https://github.com/jackbarry24/GrePT
Keywords: GPT,OpenAI,GPT-3
Requires-Python: >=3.9
License-File: LICENSE.md
Requires-Dist: openai >=0.27.2
Requires-Dist: termcolor >=2.2.0
Requires-Dist: tiktoken >=0.3.3
Requires-Dist: rich >=13.3.4
